memory_layer/__init__.py
memory_layer/client.py
memory_layer/utils.py
memory_layer-0.1.0.dist-info/licenses/LICENSE
memory_layer-0.1.0.dist-info/METADATA
memory_layer-0.1.0.dist-info/WHEEL
memory_layer-0.1.0.dist-info/top_level.txt
memory_layer-0.1.0.dist-info/RECORD
