Metadata-Version: 2.4
Name: memory-layer
Version: 0.1.0
Summary: Persistent memory layer for AI coding assistants
Author: Your Name
Author-email: Memory Layer Team <contact@memory-layer.com>
License: MIT
Project-URL: Homepage, https://github.com/your-org/memory-layer
Project-URL: Documentation, https://docs.memory-layer.com
Project-URL: Repository, https://github.com/your-org/memory-layer
Project-URL: Issues, https://github.com/your-org/memory-layer/issues
Keywords: memory,ai,assistant,vector,search
Classifier: Development Status :: 4 - Beta
Classifier: Intended Audience :: Developers
Classifier: License :: OSI Approved :: MIT License
Classifier: Programming Language :: Python :: 3
Classifier: Programming Language :: Python :: 3.7
Classifier: Programming Language :: Python :: 3.8
Classifier: Programming Language :: Python :: 3.9
Classifier: Programming Language :: Python :: 3.10
Classifier: Programming Language :: Python :: 3.11
Classifier: Programming Language :: Python :: 3.12
Requires-Python: >=3.7
License-File: LICENSE
Requires-Dist: requests>=2.31.0
Provides-Extra: dev
Requires-Dist: pytest>=7.0.0; extra == "dev"
Requires-Dist: pytest-cov>=4.0.0; extra == "dev"
Requires-Dist: black>=23.0.0; extra == "dev"
Requires-Dist: flake8>=6.0.0; extra == "dev"
Requires-Dist: mypy>=1.0.0; extra == "dev"
Dynamic: author
Dynamic: license-file
Dynamic: requires-python
